src/__init__.py
src/__main__.py
src/dice.py
src/yaml.py
src/sources/armors.yaml
src/sources/backgrounds.yaml
src/sources/classes.yaml
src/sources/feats.yaml
src/sources/languages.yaml
src/sources/races.yaml
src/sources/skills.yaml
src/sources/subclasses.yaml
src/sources/subraces.yaml
src/sources/tools.yaml
src/sources/weapons.yaml
yari-20.12b2.dist-info/LICENSE
yari-20.12b2.dist-info/METADATA
yari-20.12b2.dist-info/WHEEL
yari-20.12b2.dist-info/entry_points.txt
yari-20.12b2.dist-info/top_level.txt
yari-20.12b2.dist-info/RECORD
