Metadata-Version: 2.1
Name: yari
Version: 20.12b2
Summary: Generate 5th edition Dungeons & Dragons characters.
Home-page: https://taylormarcus.github.io/Yari/
Author: Marcus T Taylor
License: MIT
Platform: UNKNOWN
Classifier: Development Status :: 4 - Beta
Classifier: Environment :: Console
Classifier: Programming Language :: Python :: 3
Classifier: Topic :: Games/Entertainment :: Role-Playing
Requires-Python: >=3.0
Requires-Dist: aiohttp
Requires-Dist: beautifulsoup4
Requires-Dist: click
Requires-Dist: PyYAML
